rv_profile/CallStack.py
rv_profile/cli.py
rv_profile/colors.py
rv_profile/rv_profile.py
rv_profile/FlameGraph/.travis.yml
rv_profile/FlameGraph/README.md
rv_profile/FlameGraph/aix-perf.pl
rv_profile/FlameGraph/difffolded.pl
rv_profile/FlameGraph/example-dtrace-stacks.txt
rv_profile/FlameGraph/example-dtrace.svg
rv_profile/FlameGraph/example-perf-stacks.txt.gz
rv_profile/FlameGraph/example-perf.svg
rv_profile/FlameGraph/files.pl
rv_profile/FlameGraph/flamegraph.pl
rv_profile/FlameGraph/jmaps
rv_profile/FlameGraph/pkgsplit-perf.pl
rv_profile/FlameGraph/range-perf.pl
rv_profile/FlameGraph/record-test.sh
rv_profile/FlameGraph/stackcollapse-aix.pl
rv_profile/FlameGraph/stackcollapse-bpftrace.pl
rv_profile/FlameGraph/stackcollapse-chrome-tracing.py
rv_profile/FlameGraph/stackcollapse-elfutils.pl
rv_profile/FlameGraph/stackcollapse-faulthandler.pl
rv_profile/FlameGraph/stackcollapse-gdb.pl
rv_profile/FlameGraph/stackcollapse-go.pl
rv_profile/FlameGraph/stackcollapse-ibmjava.pl
rv_profile/FlameGraph/stackcollapse-instruments.pl
rv_profile/FlameGraph/stackcollapse-java-exceptions.pl
rv_profile/FlameGraph/stackcollapse-jstack.pl
rv_profile/FlameGraph/stackcollapse-ljp.awk
rv_profile/FlameGraph/stackcollapse-perf-sched.awk
rv_profile/FlameGraph/stackcollapse-perf.pl
rv_profile/FlameGraph/stackcollapse-pmc.pl
rv_profile/FlameGraph/stackcollapse-recursive.pl
rv_profile/FlameGraph/stackcollapse-sample.awk
rv_profile/FlameGraph/stackcollapse-stap.pl
rv_profile/FlameGraph/stackcollapse-vsprof.pl
rv_profile/FlameGraph/stackcollapse-vtune-mc.pl
rv_profile/FlameGraph/stackcollapse-vtune.pl
rv_profile/FlameGraph/stackcollapse-wcp.pl
rv_profile/FlameGraph/stackcollapse-xdebug.php
rv_profile/FlameGraph/stackcollapse.pl
rv_profile/FlameGraph/test.sh
rv_profile/FlameGraph/demos/README
rv_profile/FlameGraph/demos/brkbytes-mysql.svg
rv_profile/FlameGraph/demos/cpu-grep.svg
rv_profile/FlameGraph/demos/cpu-illumos-ipdce.svg
rv_profile/FlameGraph/demos/cpu-illumos-syscalls.svg
rv_profile-0.2.2.dist-info/METADATA
rv_profile-0.2.2.dist-info/WHEEL
rv_profile-0.2.2.dist-info/entry_points.txt
rv_profile-0.2.2.dist-info/top_level.txt
rv_profile-0.2.2.dist-info/RECORD
