Metadata-Version: 2.2
Name: rv_profile
Version: 0.2.2
Summary: A tool for generating flamegraphs of RISC-V programs running on RTL simulations
Author-email: Vincenzo Petrolo <vincenzo.petrolo99@gmail.com>
License: MIT
Requires-Python: >=3.7
Requires-Dist: pylibfst==0.2.0
Requires-Dist: wal-lang==0.8.2
